[{"fiscal_code":"05967900969","piva":"05967900969","cciaa":"MI","rea":1862954,"name":"H-FARM INDUSTRY S.R.L.","legal_form":"SR","registration_date":"2008-01-03","starting_date":"2008-03-01","dissolution_date":null,"toponym_code":"VIA","address":"SOLFERINO","street_number":"40","full_address":"VIA SOLFERINO 40","city":"MILANO","postal_code":"20121","province_code":"MI","country_iso_code":"IT","ateco07_code":"70.22.09"},{"fiscal_code":"03551590163","piva":"03551590163","cciaa":"BG","rea":388372,"name":"LAM SERVICE S.R.L. - IN LIQUIDAZIONE","legal_form":"SR","registration_date":"2009-02-10","starting_date":"2009-02-10","dissolution_date":"2015-12-30","toponym_code":"VIA","address":"PAPA GIOVANNI XXIII","street_number":"8/A","full_address":"VIA PAPA GIOVANNI XXIII 8/A","city":"OSIO SOPRA","postal_code":"24040","province_code":"BG","country_iso_code":"IT","ateco07_code":"63.11.11"},{"fiscal_code":"BNNSRN73D56E625X","piva":"01810580496","cciaa":"LI","rea":160142,"name":"PUNTO AUTO DI BENINI SERENA","legal_form":"DI","registration_date":"2015-03-25","starting_date":null,"dissolution_date":null,"toponym_code":"VIA","address":"PUINI","street_number":"97","full_address":"VIA PUINI 97","city":"LIVORNO","postal_code":"57128","province_code":"LI","country_iso_code":"IT","ateco07_code":"45.32"},{"fiscal_code":"04576690285","piva":"04576690285","cciaa":"PD","rea":400986,"name":"SVILUPPO ITALIA S.R.L.","legal_form":"SR","registration_date":"2011-06-22","starting_date":"2011-12-01","dissolution_date":null,"toponym_code":"PZA","address":"GIACOMO ZANELLATO","street_number":"5","full_address":"PIAZZA GIACOMO ZANELLATO 5","city":"PADOVA","postal_code":"35131","province_code":"PD","country_iso_code":"IT","ateco07_code":"68.1"},{"fiscal_code":"02253830463","piva":"02253830463","cciaa":"LU","rea":210309,"name":"TRAME E ORDITI - SOCIETA' COOPERATIVA","legal_form":"SC","registration_date":"2011-09-28","starting_date":"2011-10-03","dissolution_date":null,"toponym_code":"VIA","address":"G.B. VANNUGLI","street_number":"61","full_address":"VIA G.B. VANNUGLI 61","city":"CASTELNUOVO DI GARFAGNANA","postal_code":"55032","province_code":"LU","country_iso_code":"IT","ateco07_code":"13.2"},{"fiscal_code":"04017190234","piva":"04017190234","cciaa":"VR","rea":384730,"name":"G.L. IMPIANTI S.R.L. IN LIQUIDAZIONE","legal_form":"SR","registration_date":"2011-03-16","starting_date":"2011-04-01","dissolution_date":"2016-01-29","toponym_code":"VIA","address":"EMILIO SALGARI","street_number":"6","full_address":"VIA EMILIO SALGARI 6","city":"ISOLA DELLA SCALA","postal_code":"37063","province_code":"VR","country_iso_code":"IT","ateco07_code":null},{"fiscal_code":"ZPPDNC67B26B519L","piva":"00974980708","cciaa":"CB","rea":104589,"name":"G.Z. COSTRUZIONI DI ZAPPONE DOMENICO","legal_form":"DI","registration_date":"1999-01-25","starting_date":"1999-01-07","dissolution_date":null,"toponym_code":"CNT","address":"COLLE ARSO","street_number":"28","full_address":"CONTRADA COLLE ARSO 28","city":"CAMPOBASSO","postal_code":"86100","province_code":"CB","country_iso_code":"IT","ateco07_code":"43.39.01"},{"fiscal_code":"VZZDVD79H27L219S","piva":null,"cciaa":"TO","rea":940613,"name":"VOZZO DAVIDE","legal_form":"DI","registration_date":"2000-08-31","starting_date":"2000-08-31","dissolution_date":"2002-12-31","toponym_code":"VIA","address":"XXIV MAGGIO","street_number":"49","full_address":"VIA XXIV MAGGIO 49","city":"NOLE","postal_code":"10076","province_code":"TO","country_iso_code":"IT","ateco07_code":"43.39.01"},{"fiscal_code":"02085030233","piva":"02085030233","cciaa":"VR","rea":216656,"name":"COOPERATIVA SOCIALE CERCATE","legal_form":"SC","registration_date":"1989-02-08","starting_date":"1989-03-01","dissolution_date":null,"toponym_code":"VIA","address":"BRAMANTE","street_number":"15","full_address":"VIA BRAMANTE 15","city":"VERONA","postal_code":"37138","province_code":"VR","country_iso_code":"IT","ateco07_code":"87"},{"fiscal_code":"01557100193","piva":"01557100193","cciaa":"CR","rea":182344,"name":"PROPRIETA' 3 SOCIETA' A RESPONSABILITA' LIMITATA SEMPLIFICATA","legal_form":"SU","registration_date":"2012-10-05","starting_date":"2012-10-15","dissolution_date":null,"toponym_code":"VIA","address":"GUARNERI DEL GESU'","street_number":"20","full_address":"VIA GUARNERI DEL GESU' 20","city":"CREMONA","postal_code":"26100","province_code":"CR","country_iso_code":"IT","ateco07_code":"68.31"},{"fiscal_code":"01456670445","piva":"01456670445","cciaa":"AP","rea":136200,"name":"COOPERATIVA SOCIALE ARCOBALENO SOC. COOP. A R. L.","legal_form":"CL","registration_date":"1995-10-09","starting_date":"1995-11-20","dissolution_date":"2016-01-27","toponym_code":"VIA","address":"CENCIARINI","street_number":"33/A","full_address":"VIA CENCIARINI 33/A","city":"FOLIGNANO","postal_code":"63084","province_code":"AP","country_iso_code":"IT","ateco07_code":"81.2"},{"fiscal_code":"GMMNGL55B18B609D","piva":"02777770542","cciaa":"PG","rea":242383,"name":"GIOMMI ANGELO","legal_form":"DI","registration_date":"2005-05-10","starting_date":null,"dissolution_date":null,"toponym_code":"VIA","address":"SALA","street_number":"32","full_address":"VIA SALA 32","city":"BETTONA","postal_code":"06084","province_code":"PG","country_iso_code":"IT","ateco07_code":null},{"fiscal_code":"PSNDBR78S69C957O","piva":"04170080263","cciaa":"TV","rea":328713,"name":"DERBY DI PASIN DEBORA","legal_form":"DI","registration_date":"2007-09-24","starting_date":"2007-09-06","dissolution_date":"2014-01-28","toponym_code":"VIA","address":"BRANDOLINI","street_number":"42","full_address":"VIA BRANDOLINI 42","city":"PIEVE DI SOLIGO","postal_code":"31053","province_code":"TV","country_iso_code":"IT","ateco07_code":"32.99.9"},{"fiscal_code":"04255700371","piva":"04255700371","cciaa":"VI","rea":337718,"name":"AIREKO S.R.L","legal_form":"SR","registration_date":"2010-02-08","starting_date":null,"dissolution_date":"2016-01-28","toponym_code":"VIA","address":"MURARONI","street_number":"80","full_address":"VIA MURARONI 80","city":"BRENDOLA","postal_code":"36040","province_code":"VI","country_iso_code":"IT","ateco07_code":"28.13"},{"fiscal_code":"SRTLRD45M22C384A","piva":"01770310264","cciaa":"TV","rea":357024,"name":"SARTOR ALFREDO","legal_form":"DI","registration_date":"2012-04-23","starting_date":"2012-04-10","dissolution_date":"2015-12-31","toponym_code":"VIA","address":"DECUMANA","street_number":"2","full_address":"VIA DECUMANA 2","city":"CAVASO DEL TOMBA","postal_code":"31034","province_code":"TV","country_iso_code":"IT","ateco07_code":"01.5"},{"fiscal_code":"04706900265","piva":"04706900265","cciaa":"TV","rea":371763,"name":"SUOLIFICIO MONTESUOLE S.R.L.","legal_form":"SR","registration_date":"2014-12-29","starting_date":"2015-01-01","dissolution_date":null,"toponym_code":"VIA","address":"MARTINELLA","street_number":"49","full_address":"VIA MARTINELLA 49","city":"MONTEBELLUNA","postal_code":"31044","province_code":"TV","country_iso_code":"IT","ateco07_code":"22.19.01"},{"fiscal_code":"CSTGNN80S26C351I","piva":"04964910873","cciaa":"CT","rea":333303,"name":"CASTORINA GIOVANNI BATTISTA","legal_form":"DI","registration_date":"2012-03-08","starting_date":null,"dissolution_date":"2016-02-10","toponym_code":"VIA","address":"RICCA","street_number":"10/12","full_address":"VIA RICCA 10/12","city":"ACI CASTELLO","postal_code":"95021","province_code":"CT","country_iso_code":"IT","ateco07_code":"47.81.02"},{"fiscal_code":"PNRDNL71E62L259I","piva":"02148640515","cciaa":"AR","rea":165346,"name":"ALICE BOTTEGA TESSILE DI PANARIELLO DANIELA","legal_form":"DI","registration_date":"2013-04-16","starting_date":null,"dissolution_date":null,"toponym_code":"VIA","address":"SAN LAZZO","street_number":"4","full_address":"VIA SAN LAZZO 4","city":"CASTIGLION FIORENTINO","postal_code":"52043","province_code":"AR","country_iso_code":"IT","ateco07_code":null},{"fiscal_code":"01711510857","piva":"01711510857","cciaa":"CL","rea":93092,"name":"FALEGNAMERIA EURO ARREDI S.R.L.","legal_form":"SU","registration_date":"2004-12-03","starting_date":"2007-04-02","dissolution_date":null,"toponym_code":"VIA","address":"PIETRO MASCAGNI","street_number":"28","full_address":"VIA PIETRO MASCAGNI 28","city":"SAN CATALDO","postal_code":"93017","province_code":"CL","country_iso_code":"IT","ateco07_code":"16.23.2"},{"fiscal_code":"02846180640","piva":"02846180640","cciaa":"AV","rea":187279,"name":"DEMA S.R.L.","legal_form":"SR","registration_date":"2015-03-30","starting_date":"2015-12-28","dissolution_date":null,"toponym_code":"VIA","address":"NAZIONALE","street_number":"278","full_address":"VIA NAZIONALE 278","city":"MERCOGLIANO","postal_code":"83013","province_code":"AV","country_iso_code":"IT","ateco07_code":"73.11.02"} ]
